funciones_prueba/__init__.py
funciones_prueba/func_objetivo.py
metd_multivariable/metodos_directos.py
metd_multivariable/metodos_gradiente.py
metd_univariable/metodos_basado_derivada.py
metd_univariable/metodos_elim_regiones.py
Paquete_optimizacion_byzamm079-0.0.1.dist-info/LICENSE
Paquete_optimizacion_byzamm079-0.0.1.dist-info/METADATA
Paquete_optimizacion_byzamm079-0.0.1.dist-info/WHEEL
Paquete_optimizacion_byzamm079-0.0.1.dist-info/top_level.txt
Paquete_optimizacion_byzamm079-0.0.1.dist-info/RECORD
